pebbleauthclient/__init__.py
pebbleauthclient/auth.py
pebbleauthclient/constants.py
pebbleauthclient/errors.py
pebbleauthclient/key.py
pebbleauthclient/token_data.py
pebbleauthclient/datatypes/AuthenticatedLicenceObject.py
pebbleauthclient/datatypes/PebbleTokenData.py
pebbleauthclient/datatypes/UserObject.py
pebbleauthclient/datatypes/__init__.py
pebbleauthclient/models/AuthenticatedLicence.py
pebbleauthclient/models/PebbleAuthToken.py
pebbleauthclient/models/User.py
pebbleauthclient/models/__init__.py
pebbleauthclient-0.2.2.dist-info/METADATA
pebbleauthclient-0.2.2.dist-info/WHEEL
pebbleauthclient-0.2.2.dist-info/top_level.txt
pebbleauthclient-0.2.2.dist-info/RECORD
