Metadata-Version: 2.1
Name: pebbleauthclient
Version: 0.2.2
Summary: Pebble client tool for authenticate user and licence management written in Python
Author-email: Guillaume MODARD <guillaumemodard@gmail.com>
Project-URL: Homepage, https://pebble-solutions.github.io/pebble-auth-client-py/
Project-URL: Repository, https://github.com/pebble-solutions/pebble-auth-client-py/
Classifier: Programming Language :: Python :: 3
Classifier: License :: OSI Approved :: GNU General Public License v3 (GPLv3)
Classifier: Operating System :: OS Independent
Requires-Python: >=3.9
Requires-Dist: cryptography >=41.0.5
Requires-Dist: PyJWT >=2.8.0
